nonebot_plugin_sell_poor/__init__.py
nonebot_plugin_sell_poor/config.py
nonebot_plugin_sell_poor-0.1.0.dist-info/LICENSE
nonebot_plugin_sell_poor-0.1.0.dist-info/METADATA
nonebot_plugin_sell_poor-0.1.0.dist-info/WHEEL
nonebot_plugin_sell_poor-0.1.0.dist-info/RECORD
