Metadata-Version: 2.3
Name: nonebot-plugin-sell-poor
Version: 0.1.0
Summary: 基于 LLM 的卖若插件
License: GPL3
Author: 【夜风】NightWind
Author-email: 2125714976@qq.com
Requires-Python: >=3.9
Classifier: License :: Other/Proprietary License
Classifier: Programming Language :: Python :: 3
Classifier: Programming Language :: Python :: 3.9
Classifier: Programming Language :: Python :: 3.10
Classifier: Programming Language :: Python :: 3.11
Classifier: Programming Language :: Python :: 3.12
Classifier: Programming Language :: Python :: 3.13
Requires-Dist: PyJWT (>=2.3.0)
Requires-Dist: httpx (>=0.22.0)
Requires-Dist: nonebot-adapter-onebot (>=2.3.0)
Requires-Dist: nonebot2 (>=2.3.0,<3.0.0)
Project-URL: Documentation, https://github.com/XTxiaoting14332/nonebot-plugin-sell-poor#README.md
Project-URL: Homepage, https://github.com/XTxiaoting14332/nonebot-plugin-sell-poor
Project-URL: Repository, https://github.com/XTxiaoting14332/nonebot-plugin-sell-poor
